Workbook

Sheet Balance_Sheet
B2: Κατάσταση Αποτελεσμάτων Χρήσης | C2: 2022 | D2: 2023 | E2: 2024 | G2: Ισολογισμός | H2: 2022 | I2: 2023 | J2: 2024 | L2: Ταμειακές ροές | M2: Υπολογισμός | N2: 2023 | O2: 2024
B3: Πωλήσεις | C3: 22000 | D3: 24000 | E3: 26500 | G3: Αναπόσβεστα Πάγια | H3: 17000 | I3: 18000 | J3: 19000 | L3: Καθαρά Κέρδη | M3: από P&L | N3: =D11 -> 2652 | O3: =E11 -> 3315
B4: Κόστος Πωληθέντων | C4: 15400 | D4: 16800 | E4: 18200 | G4: Αποσβέσεις | H4: 0 | I4: 800 | J4: 1700 | L4: + Αποσβέσεις | M4: μη ταμειακό έξοδο | N4: =I4-H4 -> 800 | O4: =J4-I4 -> 900
B5: Μικτό Κέρδος | C5: =C3-C4 -> 6600 | D5: =D3-D4 -> 7200 | E5: =E3-E4 -> 8300 | G5: Καθαρά Πάγια | H5: =H3-H4 -> 17000 | I5: =I3-I4 -> 17200 | J5: =J3-J4 -> 17300 | L5: ± Μεταβολή Αποθεμάτων | M5: 5.000 − 4.500 = +500 (outflow) | N5: =-(I6-H6) -> -500 | O5: =-(J6-I6) -> -500
B6: Λειτουργικά Έξοδα | C6: 3000 | D6: 3200 | E6: 3400 | G6: Αποθέματα | H6: 4500 | I6: 5000 | J6: 5500 | L6: ± Μεταβολή Απαιτήσεων | M6: 4.000 − 3.700 = +300 (outflow) | N6: =-(I7-H7) -> -300 | O6: =-(J7-I7) -> -300
B7: EBIT | C7: =C5-C6 -> 3600 | D7: =D5-D6 -> 4000 | E7: =E5-E6 -> 4900 | G7: Απαιτήσεις | H7: 3700 | I7: 4000 | J7: 4300 | L7: ± Μεταβολή Βραχυπρ. Υποχρεώσεων | M7: 6.000 − 5.700 = +300 (inflow) | N7: =(I12-H12) -> 300 | O7: =(J12-I12) -> 200
B8: Χρηματοοικ. Έξοδα | C8: 500 | D8: 600 | E8: 650 | G8: Ταμειακά Διαθέσιμα | H8: 1500 | I8: =H8+N13 -> 3523.8 | J8: =I8+O13 -> 5478.55 | L8: Λειτουργικές Ροές (OCF) | M8: 2.652 + 800 − 500 − 300 + 300 | N8: =SUM(N3:N7) -> 2952 | O8: =SUM(O3:O7) -> 3615
B9: Κέρδη προ Φόρων | C9: =C7-C8 -> 3100 | D9: =D7-D8 -> 3400 | E9: =E7-E8 -> 4250 | G9: Σύνολο Ενεργητικού | H9: =H5+H6+H7+H8 -> 26700 | I9: =I5+I6+I7+I8 -> 29723.8 | J9: =J5+J6+J7+J8 -> 32578.55 | L9: Επενδυτικές Ροές (CapEx) | M9: 18.000 − 17.000 = +1.000 (outflow) | N9: =-(I3-H3) -> -1000 | O9: =-(J3-I3) -> -1000
B10: Φόροι (22%) | C10: =C9*0.22 -> 682 | D10: =D9*0.22 -> 748 | E10: =E9*0.22 -> 935 | G10: Ίδια Κεφάλαια | H10: 14000 | I10: =H10+D15 -> 15723.8 | J10: =I10+E15 -> 17878.55 | L10: Χρηματοδοτικές Ροές | M10: Δάνεια: 8.000 − 7.000 = +1.000 (inflow) | N10: =(I11-H11) -> 1000 | O10: =(J11-I11) -> 500
B11: Καθαρά Κέρδη | C11: =C9-C10 -> 2418 | D11: =D9-D10 -> 2652 | E11: =E9-E10 -> 3315 | G11: Μακροπρόθεσμος Δανεισμός | H11: 7000 | I11: 8000 | J11: 8500 | M11: − Μερίσματα (35% × τα καθαρά κέρδη) | N11: =-D14 -> -928.2 | O11: =-E14 -> -1160.25
B12: Αποσβέσεις | C12: =H4 -> 0 | D12: =I4-H4 -> 800 | E12: =J4-I4 -> 900 | G12: Βραχυπρόθεσμες Υποχρεώσεις | H12: 5700 | I12: 6000 | J12: 6200 | L12: Καθαρές Χρηματοδοτικές Ροές (FCF) | M12: 1000-928= | N12: =N10+N11 -> 71.8 | O12: =O10+O11 -> -660.25
B13: EBITDA | C13: =C7+C12 -> 3600 | D13: =D7+D12 -> 4800 | E13: =E7+E12 -> 5800 | G13: Σύνολο Παθητικού | H13: =H10+H11+H12 -> 26700 | I13: =I10+I11+I12 -> 29723.8 | J13: =J10+J11+J12 -> 32578.55 | L13: Καθαρή Μεταβολή Ταμείου | M13: 2.952 − 928 +72 | N13: =N8+N9+N12 -> 2023.8 | O13: =O8+O9+O12 -> 1954.75
B14: Μερίσματα (35%) | C14: =0.35*C11 -> 846.3 | D14: =0.35*D11 -> 928.2 | E14: =0.35*E11 -> 1160.25 | L14: Ταμείο Έναρξης | M14: 1500 | N14: =H8 -> 1500 | O14: =I8 -> 3523.8
B15: Αποτελεσμα εις νέον | C15: =C11-C14 -> 1571.7 | D15: =D11-D14 -> 1723.8 | E15: =E11-E14 -> 2154.75 | L15: Ταμείο Λήξης | M15: 1.500 + 2024 | N15: =N13+N14 -> 3523.8 | O15: =O13+O14 -> 5478.55

Sheet Ratios_Formulas
B2: Column1 | C2: Column2 | D2: Column3 | E2: Column4
B3: Ratio / Parameter | C3: 2023 | D3: 2024
B5: --- Valuation Parameters ---
B6: Share Price (€) | C6: 5 | D6: =C6 -> 5 | E6: τιμή ανά μετοχή
B7: Shares Outstanding (Ε000) | C7: 9000 | D7: =C7 -> 9000
B8: Market Cap (€000) | C8: =C6*C7 -> 45000 | D8: =D6*D7 -> 45000
B9: Net Debt (€000) | C9: =Balance_Sheet!I11-Balance_Sheet!I8 -> 4476.2 | D9: =Balance_Sheet!J11-Balance_Sheet!J8 -> 3021.45
B10: DPS (€) | C10: =Balance_Sheet!D14/Ratios_Formulas!C7 -> 0.10313333 | D10: =Balance_Sheet!E14/Ratios_Formulas!D7 -> 0.12891667 | E10: μερισματα ανά μετοχή (dividents per share)
B13: Average | C13: 2023 | D13: 2024
B14: Avg Inventory | C14: =(Balance_Sheet!H6+Balance_Sheet!I6)/2 -> 4750 | D14: =(Balance_Sheet!I6+Balance_Sheet!J6)/2 -> 5250 | E14: μεσα αποθέματα
B15: Avg Receivables | C15: =(Balance_Sheet!H7+Balance_Sheet!I7)/2 -> 3850 | D15: =(Balance_Sheet!I7+Balance_Sheet!J7)/2 -> 4150 | E15: μέσες απαιτήσεις
B16: Avg Equity | C16: =(Balance_Sheet!H9+Balance_Sheet!I9)/2 -> 28211.9 | D16: =(Balance_Sheet!I8+Balance_Sheet!J8)/2 -> 4501.175 | E16: μέσο ενεργητικό
B17: Avg Total Assets | C17: =(Balance_Sheet!H10+Balance_Sheet!I10)/2 -> 14861.9 | D17: =(Balance_Sheet!I9+Balance_Sheet!J9)/2 -> 31151.175 | E17: μέσα χρηματικά διαθέσιμα
B18: Total Liabilities (€000) | C18: =Balance_Sheet!I13 -> 29723.8 | D18: =Balance_Sheet!J13 -> 32578.55 | E18: συνολικό παθητικό
B19: Current Liabilities (€000)) | C19: =Balance_Sheet!I12 -> 6000 | D19: =Balance_Sheet!J12 -> 6200 | E19: βραχυπρόθεσμες
B20: Current Assets (€000) | C20: =Balance_Sheet!I6+Balance_Sheet!I7+Balance_Sheet!I8 -> 12523.8 | D20: =Balance_Sheet!J6+Balance_Sheet!J7+Balance_Sheet!J8 -> 15278.55 | E20: κυκλοφορούν
B21: Working Capital | C21: =C20-C19 -> 6523.8 | D21: =D20-D19 -> 9078.55 | E21: κυκλοφορούν - βραχυπρόθεσμες
B22: Current Ratio (x) | C22: =C20/C19 -> 2.0873 | D22: =D20/D19 -> 2.4642823 | E22: κυκλοφορούν/βραχυπρόθεσμες
B23: Quick Ratio (x) | C23: =(C20-Balance_Sheet!I6)/Ratios_Formulas!C19 -> 1.2539667 | D23: =(D20-Balance_Sheet!J6)/Ratios_Formulas!D19 -> 1.5771855 | E23: (κυκλοφορούν-αποθέματα)/βραχυπρόθεσμες
B24: Debt / Equity (x) | C24: =Balance_Sheet!I13/Balance_Sheet!I10 -> 1.89037 | D24: =Balance_Sheet!J13/Balance_Sheet!J10 -> 1.8222143 | E24: συνολικό παθητικό/ιδια κεφάλαια
B25: Net Debt/EBITDA (x) | C25: =C9/Balance_Sheet!D13 -> 0.93254167 | D25: =D9/Balance_Sheet!E13 -> 0.52093966
B26: ROE Margin | C26: =Balance_Sheet!D11/Balance_Sheet!I10 -> 0.16866152 | D26: =Balance_Sheet!E11/Balance_Sheet!J10 -> 0.18541772 | E26: return on equity (πωλήσεις/ίδια κεφάλαια)
B27: ROA Margin | C27: =Balance_Sheet!D11/Balance_Sheet!I9 -> 0.089221432 | D27: =Balance_Sheet!E11/Balance_Sheet!J9 -> 0.10175407 | E27: return on assets (πωλήσεις/σύνολο ενεργητικού)
B28: EBITDA Margin | C28: =Balance_Sheet!D13/Balance_Sheet!D3 -> 0.2 | D28: =Balance_Sheet!E13/Balance_Sheet!E3 -> 0.21886792 | E28: ebidta/πωλήσεις
B29: Net Profit Margin | C29: =Balance_Sheet!D11/Balance_Sheet!D3 -> 0.1105 | D29: =Balance_Sheet!E11/Balance_Sheet!E3 -> 0.12509434 | E29: καθαρό κέρδος/πωλήσεις
B30: Inventory Turnover Days | C30: =365/(Balance_Sheet!D4/Ratios_Formulas!C14) -> 103.1994 | D30: =365/(Balance_Sheet!E4/Ratios_Formulas!D14) -> 105.28846 | E30: 365/(κοστος πωληθέντων/μέσα αποθέματα)
B31: Receivables Days | C31: =365/(Balance_Sheet!D4/Ratios_Formulas!C15) -> 83.645833 | D31: =365/(Balance_Sheet!E4/Ratios_Formulas!D15) -> 83.228022 | E31: 365/(κόστος πωληθέντων/μέσες απαιτήσεις)
B32: Total Asset Turnover (x) | C32: =Balance_Sheet!D4/Ratios_Formulas!C18 -> 0.56520364 | D32: =Balance_Sheet!E4/Ratios_Formulas!D18 -> 0.55864979 | E32: κόστος πωληθέντων/total assets
B33: Interest Coverage (x) | C33: =Balance_Sheet!D7/Balance_Sheet!D8 -> 6.6666667 | D33: =Balance_Sheet!E7/Balance_Sheet!E8 -> 7.5384615 | E33: ebit/χρηματοϊκονομικά έξοδα
B34: EPS (€) | C34: =Balance_Sheet!D11/Ratios_Formulas!C7 -> 0.29466667 | D34: =Balance_Sheet!E11/Ratios_Formulas!D7 -> 0.36833333 | E34: earnings per share (κέρδη/αριθμό μετοχών)
B35: BVPS (€) | C35: =Balance_Sheet!I10/Ratios_Formulas!C7 -> 1.7470889 | D35: =Balance_Sheet!J10/Ratios_Formulas!D7 -> 1.9865056 | E35: book value per share (ίδια κεφ./αριθμό μετοχών)
B36: P/E (x) | C36: =(C6*C7)/Balance_Sheet!D11 -> 16.968326 | D36: =(D6*D7)/Balance_Sheet!E11 -> 13.574661 | E36: χρηματιστηριακή αξία/κέρδη
B37: P/BV (x) | C37: =(C6*C7)/Balance_Sheet!I10 -> 2.8619036 | D37: =(D6*D7)/Balance_Sheet!J10 -> 2.5169826 | E37: χρηματιστηριακή αξία/ίδια κεφάλαια
B38: EV/EBITDA (x) | C38: =(C6*C7+C9)/Balance_Sheet!D13 -> 10.307542 | D38: =(D6*D7+D9)/Balance_Sheet!E13 -> 8.2795603 | E38: (enterprise value = χρημ.αξία + net debt)/ ebidta
B39: Dividend Yield | C39: =C10/C6 -> 0.020626667 | D39: =D10/D6 -> 0.025783333 | E39: κακο για ελληνικό χρηματιστήριο (Οπαπ περιπου 8%)
